disgames/__init__.py
disgames/__main__.py
disgames/cog.py
disgames/constants.py
disgames/errors.py
disgames/mixins/__init__.py
disgames/mixins/akinator.py
disgames/mixins/akinator_buttons.py
disgames/mixins/battleship.py
disgames/mixins/blackjack.py
disgames/mixins/blackjack_buttons.py
disgames/mixins/checkers.py
disgames/mixins/chess.py
disgames/mixins/connect4.py
disgames/mixins/hangman.py
disgames/mixins/madlib.py
disgames/mixins/minesweeper.py
disgames/mixins/rps.py
disgames/mixins/rps_buttons.py
disgames/mixins/snake.py
disgames/mixins/snl.py
disgames/mixins/soko.py
disgames/mixins/sudoko.py
disgames/mixins/ttt.py
disgames/mixins/ttt_buttons.py
disgames/mixins/ttt_reactions.py
disgames/mixins/two048.py
disgames/mixins/uno.py
disgames-2.3.0.dist-info/LICENSE
disgames-2.3.0.dist-info/METADATA
disgames-2.3.0.dist-info/WHEEL
disgames-2.3.0.dist-info/top_level.txt
disgames-2.3.0.dist-info/RECORD
