Metadata-Version: 2.1
Name: disgames
Version: 2.3.0
Summary: A games module that can be used to instantly add games to your discord bot
Home-page: https://github.com/andrewthederp/Disgames
Author: andrew
Maintainer: Marcus
License: Apache
Platform: UNKNOWN
Classifier: Development Status :: 3 - Alpha
Classifier: Intended Audience :: Developers
Classifier: Topic :: Software Development :: Build Tools
Classifier: License :: OSI Approved :: MIT License
Classifier: Programming Language :: Python :: 3
Classifier: Programming Language :: Python :: 3.6
Classifier: Programming Language :: Python :: 3.7
Classifier: Programming Language :: Python :: 3.8
Classifier: Programming Language :: Python :: 3.9
Requires-Python: >=3.6
License-File: LICENSE
Requires-Dist: aiohttp
Requires-Dist: chess
Requires-Dist: stockfish
Requires-Dist: akinator.py
